[
    {
        "producto_id": 1,
        "nombre": "Pikachu",
        "precio": "550",
        "descripcion": "Electrizante Pikachu para entrenadores arriesgados",
        "imagen1": "pikachu-1.jpg",
        "imagen2": "pikachu-2.jpg",
        "imagen3": "pikachu-3.jpg",
        "imagen_descripcion": "slip de pikachu",
        "tabla de talles": "talles.jpg",
        "imagen_descripcion_talles": "tabla de talles"
    },
    {
        "producto_id": 2,
        "nombre": "Bulbasaur",
        "precio": "450",
        "descripcion": "Fiel amigo, primero de la Pokédex y excelente para criar. Cómo una planta, con cuidado y dedicación podrás lograr hacer que crezca grande y fuerte.",
        "imagen1": "bulbasaur-1.jpg",
        "imagen2": "bulbasaur-2.jpg",
        "imagen3": "bulbasaur-3.jpg",
        "imagen_descripcion": "slip de bulbasaur",
        "tabla de talles": "talles.jpg",
        "imagen_descripcion_talles": "tabla de talles"
    },
    {
        "producto_id": 3,
        "nombre": "Charmander",
        "precio": "490",
        "descripcion": "Si lo tuyo es el fuego. Tu Pokémon ideal es Charmander. Ideal para tus primeras batallas",
        "imagen1": "charmander-1.jpg",
        "imagen2": "charmander-2.jpg",
        "imagen3": "charmander-3.jpg",
        "imagen_descripcion": "slip de charmander",
        "tabla de talles": "talles.jpg",
        "imagen_descripcion_talles": "tabla de talles"
    },
    {
        "producto_id": 4,
        "nombre": "Squirtle",
        "precio": "470",
        "descripcion": "Simpático y alegre. Pokémon tipo Agua. Adaptable a cualquier hábitat. Perfecto para iniciar en tu camino a ser un maestro Pokémon.",
        "imagen1": "squirtle-1.jpg",
        "imagen2": "squirtle-2.jpg",
        "imagen3": "squirtle-3.jpg",
        "imagen_descripcion": "slip de squirtle",
        "tabla de talles": "talles.jpg",
        "imagen_descripcion_talles": "tabla de talles"
    },
    {
        "producto_id": 5,
        "nombre": "Jiggypuff",
        "precio": "420",
        "descripcion": "No te dejes atrapar por sus dulces encantos, su pureza y poder mágico. Con un Pokémon Hada marcaras la diferencia",
        "imagen1": "jiggypuff-1.jpg",
        "imagen2": "jiggypuff-2.jpg",
        "imagen3": "jiggypuff-3.jpg",
        "imagen_descripcion": "slip de jiggypuff",
        "tabla de talles": "talles.jpg",
        "imagen_descripcion_talles": "tabla de talles"
    },
    {
        "producto_id": 6,
        "nombre": "Eevee",
        "precio": "560",
        "descripcion": "No cualquier maestro puede criar un Eevee⭐ Con 8 evoluciones, este zorrito tipo normal podes ganar todas las batallas",
        "imagen1": "eevee-1.jpg",
        "imagen2": "eevee-2.jpg",
        "imagen3": "eevee-3.jpg",
        "imagen_descripcion": "slip de eevee",
        "tabla de talles": "talles.jpg",
        "imagen_descripcion_talles": "tabla de talles"
    },
    {
        "producto_id": 7,
        "nombre": "Pokebola",
        "precio": "435",
        "descripcion": "Es necesario que tengas tu Pokebola para que puedas capturar y transportar tus Pokémones ",
        "imagen1": "pokebola-1.jpg",
        "imagen2": "pokebola-2.jpg",
        "imagen3": "pokebola-3.jpg",
        "imagen_descripcion": "slip de pokebola",
        "tabla de talles": "talles.jpg",
        "imagen_descripcion_talles": "tabla de talles"
    },
    {
        "producto_id": 8,
        "nombre": "Gengar",
        "precio": "560",
        "descripcion": "Divertido, de imponentes ojos rojos, sonrisa larga y burlona. Gengar sera tu compañero de aventuras ",
        "imagen1": "gengar-1.jpg",
        "imagen2": "gengar-2.jpg",
        "imagen3": "gengar-3.jpg",
        "imagen_descripcion": "slip de gengar",
        "tabla de talles": "talles.jpg",
        "imagen_descripcion_talles": "tabla de talles"
    },
    {
        "producto_id": 9,
        "nombre": "Meowth",
        "precio": "550",
        "descripcion": "Prepárense para los problemas. Y más vale que teman ",
        "imagen1": "meowth-1.jpg",
        "imagen2": "meowth-2.jpg",
        "imagen3": "meowth-3.jpg",
        "imagen_descripcion": "slip de meowth",
        "tabla de talles": "talles.jpg",
        "imagen_descripcion_talles": "tabla de talles"
    },
    {
        "producto_id": 10,
        "nombre": "Snorlax",
        "precio": "490",
        "descripcion": "Que no te asusté su tamaño!!! Y su profundo sueño ",
        "imagen1": "snorlax-1.jpg",
        "imagen2": "snorlax-2.jpg",
        "imagen3": "snorlax-3.jpg",
        "imagen_descripcion": "slip de snorlax",
        "tabla de talles": "talles.jpg",
        "imagen_descripcion_talles": "tabla de talles"
    },
    {
        "producto_id": 11,
        "nombre": "Greninja",
        "precio": "410",
        "descripcion": "Sumamente rápido, puede aparecer y desaparecer de improvisto. ",
        "imagen1": "greninja-1.jpg",
        "imagen2": "greninja-2.jpg",
        "imagen3": "greninja-3.jpg",
        "imagen_descripcion": "slip de greninja",
        "tabla de talles": "talles.jpg",
        "imagen_descripcion_talles": "tabla de talles"
    },
    {
        "producto_id": 12,
        "nombre": "Stitch",
        "precio": "590",
        "descripcion": "¿ Por qué cada vez que vemos un Stitch lo queremos abrazar? ",
        "imagen1": "stitch-1.jpg",
        "imagen2": "stitch-2.jpg",
        "imagen3": "stitch-3.jpg",
        "imagen_descripcion": "slip de stitch",
        "tabla de talles": "talles.jpg",
        "imagen_descripcion_talles": "tabla de talles"
    },
    {
        "producto_id": 13,
        "nombre": "Luna",
        "precio": "630",
        "descripcion": "Nosotros éramos amantes incluso antes de haber nacido en este mundo ",
        "imagen1": "luna-1.jpg",
        "imagen2": "luna-2.jpg",
        "imagen3": "luna-3.jpg",
        "imagen_descripcion": "slip de luna",
        "tabla de talles": "talles.jpg",
        "imagen_descripcion_talles": "tabla de talles"
    },
    {
        "producto_id": 14,
        "nombre": "Artemis",
        "precio": "630",
        "descripcion": "Eres el amor de mis 7 vidas ",
        "imagen1": "artemis-1.jpg",
        "imagen2": "artemis-2.jpg",
        "imagen3": "artemis-3.jpg",
        "imagen_descripcion": "slip de artemis",
        "tabla de talles": "talles.jpg",
        "imagen_descripcion_talles": "tabla de talles"
    },
    {
        "producto_id": 15,
        "nombre": "Agumon",
        "precio": "620",
        "descripcion": "Fiel compañero de Taichi. Te protegerá con su flama bebé  ",
        "imagen1": "agumon-1.jpg",
        "imagen2": "agumon-2.jpg",
        "imagen3": "agumon-3.jpg",
        "imagen_descripcion": "slip de agumon",
        "tabla de talles": "talles.jpg",
        "imagen_descripcion_talles": "tabla de talles"
    },
    {
        "producto_id": 16,
        "nombre": "Gabumon",
        "precio": "620",
        "descripcion": "Compañero de Yaka, valiente, amistoso y tímido. Te protegerá con su fuego azul ",
        "imagen1": "gabumon-1.jpg",
        "imagen2": "gabumon-2.jpg",
        "imagen3": "gabumon-3.jpg",
        "imagen_descripcion": "slip de gabumon",
        "tabla de talles": "talles.jpg",
        "imagen_descripcion_talles": "tabla de talles"
    },
    {
        "producto_id": 17,
        "nombre": "Cosmo",
        "precio": "460",
        "descripcion": "Lo que todos hemos querido desde niños, tener nuestro padrino mágico   ",
        "imagen1": "cosmo-1.jpg",
        "imagen2": "cosmo-2.jpg",
        "imagen3": "cosmo-3.jpg",
        "imagen_descripcion": "slip de cosmo",
        "tabla de talles": "talles.jpg",
        "imagen_descripcion_talles": "tabla de talles"
    },
    {
        "producto_id": 18,
        "nombre": "Wanda",
        "precio": "460",
        "descripcion": "Para cumplir cualquier deseo fuera de reglas ",
        "imagen1": "wanda-1.jpg",
        "imagen2": "wanda-2.jpg",
        "imagen3": "wanda-3.jpg",
        "imagen_descripcion": "slip de wanda",
        "tabla de talles": "talles.jpg",
        "imagen_descripcion_talles": "tabla de talles"
    }
]